{
     "options": {
          "title": "Vérification Magazine Arte Reportage & Production internes"
     },
     "graph": {
          "INF_1": {
               "subflow": "com",
               "title": "Gestionnaire",
               "content": "Ingest démarré",
               "gridHook": {
                    "x": 0,
                    "y": 1
               },
               "offset": {
                    "x": 0,
                    "y": 0
               },
               "targets": [
                    {
                         "target": "INF_2",
                         "versions": [
                              {
                                   "legendOut": "",
                                   "legendIn": ""
                              }
                         ],
                         "subflow": "",
                         "dashed": false,
                         "thin": false,
                         "handleOffset": 0,
                         "innerTarget": {
                              "target": -1,
                              "versions": [
                                   {
                                        "legendOut": "",
                                        "legendIn": ""
                                   }
                              ]
                         }
                    }
               ],
               "feedbacks": [
                    {
                         "target": -1,
                         "versions": [
                              {
                                   "legendOut": "",
                                   "legendIn": ""
                              }
                         ],
                         "subflow": ""
                    }
               ]
          },
          "INF_2": {
               "subflow": "user",
               "title": "Attente fin\nAnalyse\nLoudness\n&\nBaton",
               "content": "La file d'attente\nAMS est limitee à \nune combinaison :\nEviter de\nlancer restore,\n qui rendrait le\n traitement R128\nimpossible",
               "gridHook": {
                    "x": false,
                    "y": false
               },
               "offset": {
                    "x": 0,
                    "y": 0
               },
               "targets": [
                    {
                         "target": "RAP",
                         "versions": [
                              {
                                   "legendOut": "",
                                   "legendIn": ""
                              }
                         ],
                         "subflow": "",
                         "largeLink": false,
                         "dashed": false,
                         "thin": false,
                         "handleOffset": 0,
                         "innerTarget": {
                              "target": -1,
                              "versions": [
                                   {
                                        "legendOut": "",
                                        "legendIn": ""
                                   }
                              ]
                         }
                    }
               ],
               "feedbacks": [
                    {
                         "target": -1,
                         "versions": [
                              {
                                   "legendOut": "",
                                   "legendIn": ""
                              }
                         ],
                         "subflow": ""
                    }
               ]
          },
          "RAP": {
               "subflow": "user",
               "title": "Analyse\nRapports\nMinetonka &\nBaton QC",
               "content": "\nSi un des audios\nn'est pas\nalignés R128\n(ou les 2 audios) :",
               "gridHook": {
                    "x": false,
                    "y": false
               },
               "offset": {
                    "x": 0,
                    "y": 0
               },
               "targets": [
                    {
                         "target": "ATT_LOUD",
                         "versions": [
                              {
                                   "legendOut": "",
                                   "legendIn": ""
                              }
                         ],
                         "subflow": "",
                         "largeLink": true,
                         "dashed": false,
                         "thin": false,
                         "handleOffset": 0,
                         "innerTarget": {
                              "target": -1,
                              "versions": [
                                   {
                                        "legendOut": "",
                                        "legendIn": ""
                                   }
                              ]
                         }
                    },
                    {
                         "target": "LOUD_PROC",
                         "versions": [
                              {
                                   "legendOut": "",
                                   "legendIn": ""
                              }
                         ],
                         "subflow": "",
                         "largeLink": false,
                         "dashed": true,
                         "thin": false,
                         "handleOffset": 0,
                         "innerTarget": {
                              "target": -1,
                              "versions": [
                                   {
                                        "legendOut": "",
                                        "legendIn": ""
                                   }
                              ]
                         }
                    }
               ],
               "feedbacks": [
                    {
                         "target": -1,
                         "versions": [
                              {
                                   "legendOut": "",
                                   "legendIn": ""
                              }
                         ],
                         "subflow": ""
                    }
               ]
          },
          "ATT_LOUD": {
               "subflow": "hypo",
               "title": "Attente\ntraitement\nLoudness",
               "gridHook": {
                    "x": false,
                    "y": false
               },
               "offset": {
                    "x": 0,
                    "y": 0
               },
               "targets": [
                    {
                         "target": "INF_3",
                         "versions": [
                              {
                                   "legendOut": "",
                                   "legendIn": ""
                              }
                         ],
                         "subflow": "",
                         "largeLink": false,
                         "dashed": false,
                         "thin": false,
                         "handleOffset": 0,
                         "innerTarget": {
                              "target": -1,
                              "versions": [
                                   {
                                        "legendOut": "",
                                        "legendIn": ""
                                   }
                              ]
                         }
                    }
               ],
               "feedbacks": [
                    {
                         "target": -1,
                         "versions": [
                              {
                                   "legendOut": "",
                                   "legendIn": ""
                              }
                         ],
                         "subflow": ""
                    }
               ]
          },
          "INF_3": {
               "subflow": "user",
               "title": "Restore\nobligatoire",
               "gridHook": {
                    "x": false,
                    "y": false
               },
               "offset": {
                    "x": 0,
                    "y": 0
               },
               "targets": [
                    {
                         "target": "R1",
                         "versions": [
                              {
                                   "legendOut": "",
                                   "legendIn": ""
                              }
                         ],
                         "subflow": "",
                         "largeLink": true,
                         "dashed": false,
                         "thin": false,
                         "handleOffset": 0,
                         "innerTarget": {
                              "target": -1,
                              "versions": [
                                   {
                                        "legendOut": "",
                                        "legendIn": ""
                                   }
                              ]
                         }
                    },
                    {
                         "target": "M061",
                         "versions": [
                              {
                                   "legendOut": "",
                                   "legendIn": ""
                              }
                         ],
                         "subflow": "user",
                         "dashed": true
                    }
               ],
               "feedbacks": [
                    {
                         "target": -1,
                         "versions": [
                              {
                                   "legendOut": "",
                                   "legendIn": ""
                              }
                         ],
                         "subflow": ""
                    }
               ]
          },
          "LOUD_PROC": {
               "subflow": "hypo",
               "subTask": "worker",
               "title": "Traitement R128\n(Loudness)",
               "content": "Pourra faire l'objet \nd'un sous-graph\ndétaillé\n\n(copie des fichiers\npour traitement,\npeu de problèmes\nrencontrés)",
               "gridHook": {
                    "x": false,
                    "y": false
               },
               "offset": {
                    "x": 0,
                    "y": 0
               },
               "targets": [
                    {
                         "target": -1,
                         "versions": [
                              {
                                   "legendOut": "",
                                   "legendIn": ""
                              }
                         ],
                         "subflow": "",
                         "largeLink": false,
                         "dashed": false,
                         "thin": false,
                         "handleOffset": 0,
                         "innerTarget": {
                              "target": -1,
                              "versions": [
                                   {
                                        "legendOut": "",
                                        "legendIn": ""
                                   }
                              ]
                         }
                    }
               ],
               "feedbacks": [
                    {
                         "target": -1,
                         "versions": [
                              {
                                   "legendOut": "",
                                   "legendIn": ""
                              }
                         ],
                         "subflow": ""
                    }
               ]
          },
          "R1": {
               "subTitle": "Attente Restore\ndepuis\nAdmira_cache",
               "gridHook": {
                    "x": false,
                    "y": false
               },
               "offset": {
                    "x": 0,
                    "y": 0
               },
               "targets": [
                    {
                         "target": "ST1",
                         "versions": [
                              {
                                   "legendOut": "",
                                   "legendIn": ""
                              }
                         ],
                         "subflow": "",
                         "largeLink": false,
                         "dashed": false,
                         "thin": false,
                         "handleOffset": 0,
                         "innerTarget": {
                              "target": -1,
                              "versions": [
                                   {
                                        "legendOut": "",
                                        "legendIn": ""
                                   }
                              ]
                         }
                    }
               ],
               "feedbacks": [
                    {
                         "target": -1,
                         "versions": [
                              {
                                   "legendOut": "",
                                   "legendIn": ""
                              }
                         ],
                         "subflow": ""
                    }
               ],
               "duration": 15,
               "receivedLinksHack": 1
          },
          "M061": {
               "subTask": "soft",
               "title": "M06 Prédiff",
               "content": "Restorer AHD",
               "gridHook": {
                    "x": false,
                    "y": false
               },
               "offset": {
                    "x": 0,
                    "y": 0
               },
               "targets": [
                    {
                         "target": "AR",
                         "versions": [
                              {
                                   "legendOut": "",
                                   "legendIn": ""
                              }
                         ]
                    }
               ],
               "feedbacks": [
                    {
                         "target": -1,
                         "versions": [
                              {
                                   "legendOut": "",
                                   "legendIn": ""
                              }
                         ],
                         "subflow": ""
                    }
               ],
               "duration": 5,
               "receivedLinksHack": 1,
               "emittedLinksHack": 1
          },
          "M2": {
               "subTask": "storage",
               "title": "Admira_cache",
               "subTitle": "Mediagrid",
               "gridHook": {
                    "x": false,
                    "y": 3
               },
               "offset": {
                    "x": 0,
                    "y": 0
               },
               "targets": [
                    {
                         "target": "AR",
                         "versions": [
                              {
                                   "legendOut": "OP1B ID.mxf",
                                   "legendIn": ""
                              },
                              {
                                   "legendOut": "OP1B ID.avc",
                                   "legendIn": ""
                              },
                              {
                                   "legendOut": "OP1B ID.wav",
                                   "legendIn": ""
                              },
                              {
                                   "legendOut": "OP1B ID_1.wav",
                                   "legendIn": ""
                              }
                         ]
                    }
               ],
               "feedbacks": [
                    {
                         "target": -1,
                         "versions": [
                              {
                                   "legendOut": "",
                                   "legendIn": ""
                              }
                         ],
                         "subflow": ""
                    }
               ],
               "duration": 5
          },
          "AR": {
               "subTask": "worker",
               "title": "AMS\nExport_to_SHD",
               "gridHook": {
                    "x": false,
                    "y": 2
               },
               "offset": {
                    "x": 0,
                    "y": 0
               },
               "targets": [
                    {
                         "target": "SPEC",
                         "versions": [
                              {
                                   "legendOut": "OP1B ID.mxf",
                                   "legendIn": ""
                              },
                              {
                                   "legendOut": "OP1B ID.avc",
                                   "legendIn": ""
                              },
                              {
                                   "legendOut": "OP1B ID.wav",
                                   "legendIn": ""
                              },
                              {
                                   "legendOut": "OP1B ID_1.wav",
                                   "legendIn": ""
                              }
                         ],
                         "subflow": ""
                    }
               ],
               "feedbacks": [
                    {
                         "target": -1,
                         "versions": [
                              {
                                   "legendOut": "",
                                   "legendIn": ""
                              }
                         ],
                         "subflow": ""
                    }
               ],
               "duration": 15
          },
          "SPEC": {
               "subflow": "process",
               "subTask": "storage",
               "title": "PREDIFF",
               "subTitle": "Spectrum",
               "gridHook": {
                    "x": false,
                    "y": 3
               },
               "offset": {
                    "x": 0,
                    "y": 0
               },
               "targets": [
                    {
                         "target": -1,
                         "versions": [
                              {
                                   "legendOut": "OP1B ID.mxf",
                                   "legendIn": ""
                              }
                         ]
                    }
               ],
               "feedbacks": [
                    {
                         "target": -1,
                         "versions": [
                              {
                                   "legendOut": "",
                                   "legendIn": ""
                              }
                         ],
                         "subflow": ""
                    }
               ],
               "duration": 5
          },
          "ST1": {
               "subflow": "hypo",
               "subTask": "user",
               "title": "Charger\net contrôler\nFichier ST et\nAnalyse du\nRapport Ayato",
               "subTitle": "si version\nsous-titrée",
               "gridHook": {
                    "x": false,
                    "y": false
               },
               "offset": {
                    "x": 0,
                    "y": 0
               },
               "targets": [
                    {
                         "target": "TC",
                         "versions": [
                              {
                                   "legendOut": "",
                                   "legendIn": ""
                              }
                         ],
                         "subflow": "",
                         "largeLink": false,
                         "dashed": false,
                         "thin": false,
                         "handleOffset": 0,
                         "innerTarget": {
                              "target": -1,
                              "versions": [
                                   {
                                        "legendOut": "",
                                        "legendIn": ""
                                   }
                              ]
                         }
                    }
               ],
               "feedbacks": [
                    {
                         "target": -1,
                         "versions": [
                              {
                                   "legendOut": "",
                                   "legendIn": ""
                              }
                         ],
                         "subflow": ""
                    }
               ]
          },
          "TC": {
               "subflow": "user",
               "title": "Contrôle\nTC's IN-OUT &\nDern.Image Utile",
               "subTitle": " 2 versions",
               "gridHook": {
                    "x": false,
                    "y": false
               },
               "offset": {
                    "x": 0,
                    "y": 0
               },
               "targets": [
                    {
                         "target": "VERIF1",
                         "versions": [
                              {
                                   "legendOut": "",
                                   "legendIn": ""
                              }
                         ],
                         "subflow": "",
                         "largeLink": false,
                         "dashed": false,
                         "thin": false,
                         "handleOffset": 0,
                         "innerTarget": {
                              "target": -1,
                              "versions": [
                                   {
                                        "legendOut": "",
                                        "legendIn": ""
                                   }
                              ]
                         }
                    }
               ],
               "feedbacks": [
                    {
                         "target": -1,
                         "versions": [
                              {
                                   "legendOut": "",
                                   "legendIn": ""
                              }
                         ],
                         "subflow": ""
                    }
               ]
          },
          "VERIF1": {
               "subflow": "user",
               "title": "Vérification\npar sondage\nde la version\ndans la langue\ndu présentateur",
               "content": "Relevé TC's\nHypothèses\nDéfauts",
               "gridHook": {
                    "x": false,
                    "y": false
               },
               "offset": {
                    "x": 0,
                    "y": 0
               },
               "targets": [
                    {
                         "target": "ST2",
                         "versions": [
                              {
                                   "legendOut": "",
                                   "legendIn": ""
                              }
                         ],
                         "subflow": "",
                         "largeLink": false,
                         "dashed": false,
                         "thin": false,
                         "handleOffset": 0,
                         "innerTarget": {
                              "target": -1,
                              "versions": [
                                   {
                                        "legendOut": "",
                                        "legendIn": ""
                                   }
                              ]
                         }
                    }
               ],
               "feedbacks": [
                    {
                         "target": -1,
                         "versions": [
                              {
                                   "legendOut": "",
                                   "legendIn": ""
                              }
                         ],
                         "subflow": ""
                    }
               ]
          },
          "ST2": {
               "subflow": "hypo",
               "subTask": "user",
               "title": "Charger\net contrôler\nFichier ST et\nAnalyse du\nRapport Ayato",
               "subTitle": "si version\nsous-titrée",
               "gridHook": {
                    "x": false,
                    "y": false
               },
               "offset": {
                    "x": 0,
                    "y": 0
               },
               "targets": [
                    {
                         "target": "VERIF2",
                         "versions": [
                              {
                                   "legendOut": "",
                                   "legendIn": ""
                              }
                         ],
                         "subflow": "",
                         "largeLink": false,
                         "dashed": false,
                         "thin": false,
                         "handleOffset": 0,
                         "innerTarget": {
                              "target": -1,
                              "versions": [
                                   {
                                        "legendOut": "",
                                        "legendIn": ""
                                   }
                              ]
                         }
                    }
               ],
               "feedbacks": [
                    {
                         "target": -1,
                         "versions": [
                              {
                                   "legendOut": "",
                                   "legendIn": ""
                              }
                         ],
                         "subflow": ""
                    }
               ]
          },
          "VERIF2": {
               "subflow": "user",
               "title": "Vérification\nIntégrale\nde la version\navec Voice-over",
               "content": "Repérage Options\nExtraits TV-Guide\n\nRelevé TC's\nHypothèses\nDéfauts",
               "gridHook": {
                    "x": false,
                    "y": false
               },
               "offset": {
                    "x": 0,
                    "y": 0
               },
               "targets": [
                    {
                         "target": "TVG",
                         "versions": [
                              {
                                   "legendOut": "",
                                   "legendIn": ""
                              }
                         ],
                         "subflow": "",
                         "largeLink": false,
                         "dashed": false,
                         "thin": false,
                         "handleOffset": 0,
                         "innerTarget": {
                              "target": -1,
                              "versions": [
                                   {
                                        "legendOut": "",
                                        "legendIn": ""
                                   }
                              ]
                         }
                    }
               ],
               "feedbacks": [
                    {
                         "target": -1,
                         "versions": [
                              {
                                   "legendOut": "",
                                   "legendIn": ""
                              }
                         ],
                         "subflow": ""
                    }
               ]
          },
          "TVG": {
               "subflow": "user",
               "title": "Choix Définitif\nExtrait TVG",
               "subTitle": " 2 versions",
               "gridHook": {
                    "x": false,
                    "y": false
               },
               "offset": {
                    "x": 0,
                    "y": 0
               },
               "targets": [
                    {
                         "target": "EVAL",
                         "versions": [
                              {
                                   "legendOut": "",
                                   "legendIn": ""
                              }
                         ],
                         "subflow": "",
                         "largeLink": false,
                         "dashed": false,
                         "thin": false,
                         "handleOffset": 0,
                         "innerTarget": {
                              "target": -1,
                              "versions": [
                                   {
                                        "legendOut": "",
                                        "legendIn": ""
                                   }
                              ]
                         }
                    }
               ],
               "feedbacks": [
                    {
                         "target": -1,
                         "versions": [
                              {
                                   "legendOut": "",
                                   "legendIn": ""
                              }
                         ],
                         "subflow": ""
                    }
               ]
          },
          "EVAL": {
               "subTask": "user",
               "title": "Evaluation\nde la gravité\ndes défauts",
               "subTitle": "Décision \nAcceptation / Refus",
               "gridHook": {
                    "x": false,
                    "y": false
               },
               "offset": {
                    "x": 0,
                    "y": 0
               },
               "targets": [
                    {
                         "target": "SAI",
                         "versions": [
                              {
                                   "legendOut": "",
                                   "legendIn": ""
                              }
                         ],
                         "subflow": "",
                         "largeLink": false,
                         "dashed": false,
                         "thin": false,
                         "handleOffset": 0,
                         "innerTarget": {
                              "target": -1,
                              "versions": [
                                   {
                                        "legendOut": "",
                                        "legendIn": ""
                                   }
                              ]
                         }
                    }
               ],
               "feedbacks": [
                    {
                         "target": -1,
                         "versions": [
                              {
                                   "legendOut": "",
                                   "legendIn": ""
                              }
                         ],
                         "subflow": ""
                    }
               ]
          },
          "SAI": {
               "subflow": "user",
               "subTask": "saisie",
               "title": "Saisie des\nDonnées",
               "subTitle": "Vers état \"P\"\nVers état \"H\"\nVers état \"R\"",
               "content": "Validation de l'état,\nRédaction \nnote de synthèse\ndans champs Com',\n& Inscription\nautomatique \nd'une entrée\ndans l'historique\nde vérification",
               "gridHook": {
                    "x": false,
                    "y": false
               },
               "offset": {
                    "x": 0,
                    "y": 0
               },
               "targets": [
                    {
                         "target": "NLE",
                         "versions": [
                              {
                                   "legendOut": "",
                                   "legendIn": ""
                              }
                         ],
                         "subflow": "reclam",
                         "largeLink": false,
                         "dashed": true,
                         "thin": false,
                         "handleOffset": 0,
                         "innerTarget": {
                              "target": -1,
                              "versions": [
                                   {
                                        "legendOut": "",
                                        "legendIn": ""
                                   }
                              ]
                         }
                    },
                    {
                         "target": "RECLAM",
                         "versions": [
                              {
                                   "legendOut": "",
                                   "legendIn": ""
                              }
                         ],
                         "subflow": "reclam",
                         "largeLink": false,
                         "dashed": true,
                         "thin": false,
                         "handleOffset": 0,
                         "innerTarget": {
                              "target": -1,
                              "versions": [
                                   {
                                        "legendOut": "",
                                        "legendIn": ""
                                   }
                              ]
                         }
                    },
                    {
                         "target": "COM",
                         "versions": [
                              {
                                   "legendOut": "",
                                   "legendIn": ""
                              }
                         ],
                         "subflow": "",
                         "largeLink": false,
                         "dashed": false,
                         "thin": false,
                         "handleOffset": -12,
                         "innerTarget": {
                              "target": -1,
                              "versions": [
                                   {
                                        "legendOut": "",
                                        "legendIn": ""
                                   }
                              ]
                         }
                    },
                    {
                         "target": "M062",
                         "versions": [
                              {
                                   "legendOut": "",
                                   "legendIn": ""
                              }
                         ],
                         "subflow": "",
                         "largeLink": false,
                         "dashed": false,
                         "thin": false,
                         "handleOffset": 0,
                         "innerTarget": {
                              "target": -1,
                              "versions": [
                                   {
                                        "legendOut": "",
                                        "legendIn": ""
                                   }
                              ]
                         }
                    }
               ],
               "feedbacks": [
                    {
                         "target": -1,
                         "versions": [
                              {
                                   "legendOut": "",
                                   "legendIn": ""
                              }
                         ],
                         "subflow": ""
                    }
               ]
          },
          "NLE": {
               "subflow": "hypo",
               "title": "Départ\nWorkflow\nNLE",
               "content": "Insert d'une \nrustine de version\nà version",
               "gridHook": {
                    "x": false,
                    "y": false
               },
               "offset": {
                    "x": 0,
                    "y": 0
               },
               "height": 138,
               "targets": [
                    {
                         "target": -1,
                         "versions": [
                              {
                                   "legendOut": "",
                                   "legendIn": ""
                              }
                         ],
                         "subflow": "",
                         "largeLink": false,
                         "dashed": false,
                         "thin": false,
                         "handleOffset": 0,
                         "innerTarget": {
                              "target": -1,
                              "versions": [
                                   {
                                        "legendOut": "",
                                        "legendIn": ""
                                   }
                              ]
                         }
                    }
               ],
               "feedbacks": [
                    {
                         "target": -1,
                         "versions": [
                              {
                                   "legendOut": "",
                                   "legendIn": ""
                              }
                         ],
                         "subflow": ""
                    }
               ],
               "receivedLinksHack": 1
          },
          "RECLAM": {
               "subflow": "hypo",
               "title": "Départ\nWorkflow\nRéclamation AR",
               "content": "Retour Prod.\nen urgence",
               "gridHook": {
                    "x": false,
                    "y": false
               },
               "offset": {
                    "x": 0,
                    "y": -0.5
               },
               "height": 138,
               "targets": [
                    {
                         "target": -1,
                         "versions": [
                              {
                                   "legendOut": "",
                                   "legendIn": ""
                              }
                         ],
                         "subflow": "neutral",
                         "largeLink": false,
                         "dashed": true,
                         "thin": false,
                         "handleOffset": 0,
                         "innerTarget": {
                              "target": -1,
                              "versions": [
                                   {
                                        "legendOut": "",
                                        "legendIn": ""
                                   }
                              ]
                         }
                    }
               ],
               "feedbacks": [
                    {
                         "target": -1,
                         "versions": [
                              {
                                   "legendOut": "",
                                   "legendIn": ""
                              }
                         ],
                         "subflow": ""
                    }
               ]
          },
          "COM": {
               "subflow": "com",
               "title": "Communication",
               "content": "Appel \nRégie Finale\nEM du WE PAD",
               "gridHook": {
                    "x": false,
                    "y": 1
               },
               "offset": {
                    "x": 1,
                    "y": 0
               },
               "targets": [
                    {
                         "target": -1,
                         "versions": [
                              {
                                   "legendOut": "",
                                   "legendIn": ""
                              }
                         ],
                         "subflow": "",
                         "largeLink": false,
                         "dashed": false,
                         "thin": false,
                         "handleOffset": 0,
                         "innerTarget": {
                              "target": -1,
                              "versions": [
                                   {
                                        "legendOut": "",
                                        "legendIn": ""
                                   }
                              ]
                         }
                    }
               ],
               "feedbacks": [
                    {
                         "target": -1,
                         "versions": [
                              {
                                   "legendOut": "",
                                   "legendIn": ""
                              }
                         ],
                         "subflow": ""
                    }
               ],
               "receivedLinksHack": 1
          },
          "M062": {
               "subflow": "process",
               "subTask": "soft",
               "title": "M06 Prédiff",
               "subTitle": "Fiche PADM HD",
               "gridHook": {
                    "x": false,
                    "y": 2
               },
               "offset": {
                    "x": 0,
                    "y": 0
               },
               "targets": [
                    {
                         "target": -1,
                         "versions": [
                              {
                                   "legendOut": "",
                                   "legendIn": ""
                              }
                         ],
                         "subflow": "",
                         "largeLink": false,
                         "dashed": false,
                         "thin": false,
                         "handleOffset": 0,
                         "innerTarget": {
                              "target": -1,
                              "versions": [
                                   {
                                        "legendOut": "",
                                        "legendIn": ""
                                   }
                              ]
                         }
                    }
               ],
               "feedbacks": [
                    {
                         "target": -1,
                         "versions": [
                              {
                                   "legendOut": "",
                                   "legendIn": ""
                              }
                         ],
                         "subflow": ""
                    }
               ]
          }
     }
}